{
    "piratecave": {
        "runType": "Pirate Cave",
        "runName": "Pirate Cave",
        "aliases": [
            "pcave"
        ],
        "enabled": true,
        "keyEmote": "pcaveK",
        "pingRole": null,
        "headcountEmote": "pcave",
        "headcountOnAfk": true,
        "isSplit": false,
        "vialReact": false,
        "twoPhase": false,
        "startDelay": 5000,
        "vcCap": 45,
        "timeLimit": 300,
        "keyCount": 3,
        "color": "#D2691E",
        "isExalt": false,
        "reacts": [
            "Warrior",
            "Paladin",
            "Knight",
            "Bard",
            "Priest"
        ],
        "earlyLocationCost": 15,
        "earlyLocationReacts": []
    },
    "forestmaze": {
        "runType": "Forest Maze",
        "runName": "Forest Maze",
        "aliases": [
            "forest",
            "maze"
        ],
        "enabled": true,
        "keyEmote": "forestK",
        "pingRole": null,
        "headcountEmote": "forest",
        "headcountOnAfk": true,
        "isSplit": false,
        "vialReact": false,
        "twoPhase": false,
        "startDelay": 5000,
        "vcCap": 45,
        "timeLimit": 300,
        "keyCount": 3,
        "color": "#00ff00",
        "isExalt": false,
        "reacts": [
            "Warrior",
            "Paladin",
            "Knight",
            "Bard",
            "Priest"
        ],
        "earlyLocationCost": 15,
        "earlyLocationReacts": []
    },
    "spiderden": {
        "runType": "Spider Den",
        "runName": "Spider Den",
        "aliases": [
            "spider"
        ],
        "enabled": true,
        "keyEmote": "spiderK",
        "pingRole": null,
        "headcountEmote": "spider",
        "headcountOnAfk": true,
        "isSplit": false,
        "vialReact": false,
        "twoPhase": false,
        "startDelay": 5000,
        "vcCap": 45,
        "timeLimit": 300,
        "keyCount": 3,
        "color": "#800080",
        "isExalt": false,
        "reacts": [
            "Warrior",
            "Paladin",
            "Knight",
            "Bard",
            "Priest"
        ],
        "earlyLocationCost": 15,
        "earlyLocationReacts": []
    },
    "snakepit": {
        "runType": "Snake Pit",
        "runName": "Snake Pit",
        "aliases": [
            "snake",
            "pit"
        ],
        "enabled": true,
        "keyEmote": "snakeK",
        "pingRole": null,
        "headcountEmote": "snake2",
        "headcountOnAfk": true,
        "isSplit": false,
        "vialReact": false,
        "twoPhase": false,
        "startDelay": 5000,
        "vcCap": 45,
        "timeLimit": 300,
        "keyCount": 3,
        "color": "#00ff00",
        "isExalt": false,
        "reacts": [
            "Warrior",
            "Paladin",
            "Knight",
            "Bard",
            "Priest"
        ],
        "earlyLocationCost": 15,
        "earlyLocationReacts": []
    },
    "forbiddenjungle": {
        "runType": "Forbidden Jungle",
        "runName": "Forbidden Jungle",
        "aliases": [
            "jungle"
        ],
        "enabled": true,
        "keyEmote": "jungleK",
        "pingRole": null,
        "headcountEmote": "jungle",
        "headcountOnAfk": true,
        "isSplit": false,
        "vialReact": false,
        "twoPhase": false,
        "startDelay": 5000,
        "vcCap": 45,
        "timeLimit": 300,
        "keyCount": 3,
        "color": "#00ff00",
        "isExalt": false,
        "reacts": [
            "Warrior",
            "Paladin",
            "Knight",
            "Bard",
            "Priest"
        ],
        "earlyLocationCost": 15,
        "earlyLocationReacts": []
    },
    "hive": {
        "runType": "Hive",
        "runName": "Hive",
        "aliases": [],
        "enabled": true,
        "keyEmote": "hiveK",
        "pingRole": null,
        "headcountEmote": "hive",
        "headcountOnAfk": true,
        "isSplit": false,
        "vialReact": false,
        "twoPhase": false,
        "startDelay": 5000,
        "vcCap": 45,
        "timeLimit": 300,
        "keyCount": 3,
        "color": "#",
        "isExalt": false,
        "reacts": [
            "Warrior",
            "Paladin",
            "Knight",
            "Bard",
            "Priest"
        ],
        "earlyLocationCost": 15,
        "earlyLocationReacts": []
    },
    "magicwoods": {
        "runType": "Magic Woods",
        "runName": "Magic Woods",
        "aliases": [
            "mwoods"
        ],
        "enabled": true,
        "keyEmote": "mwoodK",
        "pingRole": null,
        "headcountEmote": "mwood",
        "headcountOnAfk": true,
        "isSplit": false,
        "vialReact": false,
        "twoPhase": false,
        "startDelay": 5000,
        "vcCap": 45,
        "timeLimit": 300,
        "keyCount": 3,
        "color": "#00ff00",
        "isExalt": false,
        "reacts": [
            "UTCloakofthePlanewalker",
            "Warrior",
            "Paladin",
            "Knight",
            "Bard",
            "Priest"
        ],
        "earlyLocationCost": 15,
        "earlyLocationReacts": []
    },
    "spriteworld": {
        "runType": "Sprite World",
        "runName": "Sprite World",
        "aliases": [
            "sprite"
        ],
        "enabled": true,
        "keyEmote": "spriteK",
        "pingRole": null,
        "headcountEmote": "sprite",
        "headcountOnAfk": true,
        "isSplit": false,
        "vialReact": false,
        "twoPhase": false,
        "startDelay": 5000,
        "vcCap": 45,
        "timeLimit": 300,
        "keyCount": 3,
        "color": "#fefefe",
        "isExalt": false,
        "reacts": [
            "UTCloakofthePlanewalker",
            "Warrior",
            "Paladin",
            "Knight",
            "Bard",
            "Priest"
        ],
        "earlyLocationCost": 15,
        "earlyLocationReacts": []
    },
    "candyland": {
        "runType": "Candyland",
        "runName": "Candyland",
        "aliases": [
            "cland"
        ],
        "enabled": true,
        "keyEmote": "clandK",
        "pingRole": null,
        "headcountEmote": "cland",
        "headcountOnAfk": true,
        "isSplit": false,
        "vialReact": false,
        "twoPhase": false,
        "startDelay": 5000,
        "vcCap": 45,
        "timeLimit": 300,
        "keyCount": 3,
        "color": "#fefefe",
        "isExalt": false,
        "reacts": [
            "Warrior",
            "Paladin",
            "Knight",
            "Bard",
            "Priest"
        ],
        "earlyLocationCost": 15,
        "earlyLocationReacts": []
    },
    "undeadlair": {
        "runType": "Undead Lair",
        "runName": "Undead Lair",
        "aliases": [
            "udl"
        ],
        "enabled": true,
        "keyEmote": "udlK",
        "pingRole": null,
        "headcountEmote": "udl2",
        "headcountOnAfk": true,
        "isSplit": false,
        "vialReact": false,
        "twoPhase": false,
        "startDelay": 5000,
        "vcCap": 45,
        "timeLimit": 300,
        "keyCount": 3,
        "color": "#fefefe",
        "isExalt": false,
        "reacts": [
            "UTCloakofthePlanewalker",
            "Warrior",
            "Paladin",
            "Knight",
            "Bard",
            "Priest"
        ],
        "earlyLocationCost": 15,
        "earlyLocationReacts": []
    },
    "abyss": {
        "runType": "Abyss of Demons",
        "runName": "Abyss of Demons",
        "aliases": [],
        "enabled": true,
        "keyEmote": "abyK",
        "pingRole": null,
        "headcountEmote": "aby",
        "headcountOnAfk": true,
        "isSplit": false,
        "vialReact": false,
        "twoPhase": false,
        "startDelay": 5000,
        "vcCap": 45,
        "timeLimit": 300,
        "keyCount": 3,
        "color": "#ff0000",
        "isExalt": false,
        "reacts": [
            "UTCloakofthePlanewalker",
            "Warrior",
            "Paladin",
            "Knight",
            "Bard",
            "Priest"
        ],
        "earlyLocationCost": 15,
        "earlyLocationReacts": []
    },
    "manor": {
        "runType": "Manor",
        "runName": "Manor",
        "aliases": [],
        "enabled": true,
        "keyEmote": "manorK",
        "pingRole": null,
        "headcountEmote": "manor",
        "headcountOnAfk": true,
        "isSplit": false,
        "vialReact": false,
        "twoPhase": false,
        "startDelay": 5000,
        "vcCap": 45,
        "timeLimit": 300,
        "keyCount": 3,
        "color": "#000000",
        "isExalt": false,
        "reacts": [
            "UTCloakofthePlanewalker",
            "Warrior",
            "Paladin",
            "Knight",
            "Bard",
            "Priest"
        ],
        "earlyLocationCost": 15,
        "earlyLocationReacts": []
    },
    "sewers": {
        "runType": "Sewers",
        "runName": "Sewers",
        "aliases": [
            "sew"
        ],
        "enabled": true,
        "keyEmote": "sewerK",
        "pingRole": null,
        "headcountEmote": "sewer",
        "headcountOnAfk": true,
        "isSplit": false,
        "vialReact": false,
        "twoPhase": false,
        "startDelay": 5000,
        "vcCap": 45,
        "timeLimit": 300,
        "keyCount": 3,
        "color": "#00ff00",
        "isExalt": false,
        "reacts": [
            "UTCloakofthePlanewalker",
            "Warrior",
            "Paladin",
            "Knight",
            "Bard",
            "Trickster",
            "Priest"
        ],
        "earlyLocationCost": 15,
        "earlyLocationReacts": []
    },
    "library": {
        "runType": "Library",
        "runName": "Library",
        "aliases": [
            "lib"
        ],
        "enabled": true,
        "keyEmote": "libK",
        "pingRole": null,
        "headcountEmote": "lib2",
        "headcountOnAfk": true,
        "isSplit": false,
        "vialReact": false,
        "twoPhase": false,
        "startDelay": 5000,
        "vcCap": 45,
        "timeLimit": 300,
        "keyCount": 3,
        "color": "#000000",
        "isExalt": false,
        "reacts": [
            "UTCloakofthePlanewalker",
            "Warrior",
            "Paladin",
            "Knight",
            "Bard",
            "Trickster",
            "Priest"
        ],
        "earlyLocationCost": 15,
        "earlyLocationReacts": []
    },
    "cemetary": {
        "runType": "Cemetary",
        "runName": "Cemetary",
        "aliases": [
            "cem"
        ],
        "enabled": true,
        "keyEmote": "cemK",
        "pingRole": null,
        "headcountEmote": "cem2",
        "headcountOnAfk": true,
        "isSplit": false,
        "vialReact": false,
        "twoPhase": false,
        "startDelay": 5000,
        "vcCap": 45,
        "timeLimit": 300,
        "keyCount": 3,
        "color": "#00ff00",
        "isExalt": false,
        "reacts": [
            "STBrainoftheGolem",
            "Ogmur",
            "Curse",
            "Expose",
            "Warrior",
            "Paladin",
            "Knight",
            "Bard",
            "Trickster",
            "Priest"
        ],
        "earlyLocationCost": 15,
        "earlyLocationReacts": []
    },
    "machine": {
        "runType": "Machine",
        "runName": "Machine",
        "aliases": [],
        "enabled": true,
        "keyEmote": "machineK",
        "pingRole": null,
        "headcountEmote": "machine",
        "headcountOnAfk": true,
        "isSplit": false,
        "vialReact": false,
        "twoPhase": false,
        "startDelay": 5000,
        "vcCap": 45,
        "timeLimit": 300,
        "keyCount": 3,
        "color": "#fefefe",
        "isExalt": false,
        "reacts": [
            "Collo",
            "Slow",
            "Warrior",
            "Paladin",
            "Knight",
            "Bard",
            "Trickster",
            "Priest"
        ],
        "earlyLocationCost": 15,
        "earlyLocationReacts": []
    },
    "lab": {
        "runType": "Lab",
        "runName": "Lab",
        "aliases": [
            "mlab"
        ],
        "enabled": true,
        "keyEmote": "labK",
        "pingRole": null,
        "headcountEmote": "lab2",
        "headcountOnAfk": true,
        "isSplit": false,
        "vialReact": false,
        "twoPhase": false,
        "startDelay": 5000,
        "vcCap": 45,
        "timeLimit": 300,
        "keyCount": 3,
        "color": "#ff00ff",
        "isExalt": false,
        "reacts": [
            "UTCloakofthePlanewalker",
            "Warrior",
            "Paladin",
            "Knight",
            "Bard",
            "Trickster",
            "Priest"
        ],
        "earlyLocationCost": 15,
        "earlyLocationReacts": []
    },
    "parasite": {
        "runType": "Parasite",
        "runName": "Parasite",
        "aliases": [
            "para"
        ],
        "enabled": true,
        "keyEmote": "parasiteK",
        "pingRole": null,
        "headcountEmote": "parasite2",
        "headcountOnAfk": true,
        "isSplit": false,
        "vialReact": false,
        "twoPhase": false,
        "startDelay": 5000,
        "vcCap": 45,
        "timeLimit": 300,
        "keyCount": 3,
        "color": "#ff0000",
        "isExalt": false,
        "reacts": [
            "UTCloakofthePlanewalker",
            "daze",
            "Warrior",
            "Paladin",
            "Knight",
            "Bard",
            "Priest"
        ],
        "earlyLocationCost": 15,
        "earlyLocationReacts": []
    },
    "beachzone": {
        "runType": "Beachzone",
        "runName": "Beachzone",
        "aliases": [],
        "enabled": true,
        "keyEmote": "beachK",
        "pingRole": null,
        "headcountEmote": "beach",
        "headcountOnAfk": true,
        "isSplit": false,
        "vialReact": false,
        "twoPhase": false,
        "startDelay": 5000,
        "vcCap": 45,
        "timeLimit": 300,
        "keyCount": 3,
        "color": "#ffff00",
        "isExalt": false,
        "reacts": [
            "Mystic",
            "Warrior",
            "Paladin",
            "Knight",
            "Bard",
            "Priest"
        ],
        "earlyLocationCost": 15,
        "earlyLocationReacts": []
    },
    "davy": {
        "runType": "Davy's",
        "runName": "Davy's",
        "aliases": [],
        "enabled": true,
        "keyEmote": "davyK",
        "pingRole": null,
        "headcountEmote": "davy",
        "headcountOnAfk": true,
        "isSplit": false,
        "vialReact": false,
        "twoPhase": false,
        "startDelay": 5000,
        "vcCap": 45,
        "timeLimit": 300,
        "keyCount": 3,
        "color": "#0000ff",
        "isExalt": false,
        "reacts": [
            "UTCloakofthePlanewalker",
            "Warrior",
            "Paladin",
            "Knight",
            "Bard",
            "Trickster",
            "Priest"
        ],
        "earlyLocationCost": 15,
        "earlyLocationReacts": []
    },
    "mountaintemple": {
        "runType": "Mountain Temple",
        "runName": "Mountain Temple",
        "aliases": [
            "mt"
        ],
        "enabled": true,
        "keyEmote": "mtK",
        "pingRole": null,
        "headcountEmote": "mt",
        "headcountOnAfk": true,
        "isSplit": false,
        "vialReact": false,
        "twoPhase": false,
        "startDelay": 5000,
        "vcCap": 45,
        "timeLimit": 300,
        "keyCount": 3,
        "color": "#000000",
        "isExalt": false,
        "reacts": [
            "UTCloakofthePlanewalker",
            "tomeOfTheMushroomTribesFungal",
            "daze",
            "Warrior",
            "Paladin",
            "Knight",
            "Bard",
            "Trickster",
            "Priest"
        ],
        "earlyLocationCost": 15,
        "earlyLocationReacts": []
    },
    "lair": {
        "runType": "Lair of Draconis",
        "runName": "Lair of Draconis",
        "aliases": [
            "lod"
        ],
        "enabled": true,
        "keyEmote": "lodK",
        "pingRole": null,
        "headcountEmote": "lod",
        "headcountOnAfk": true,
        "isSplit": false,
        "vialReact": false,
        "twoPhase": false,
        "startDelay": 5000,
        "vcCap": 45,
        "timeLimit": 300,
        "keyCount": 3,
        "color": "#ffff00",
        "isExalt": false,
        "reacts": [
            "Ogmur",
            "Curse",
            "Expose",
            "Warrior",
            "Paladin",
            "Knight",
            "Bard",
            "Priest"
        ],
        "earlyLocationCost": 15,
        "earlyLocationReacts": []
    },
    "deadwaterdocks": {
        "runType": "Deadwater Docks",
        "runName": "Deadwater Docks",
        "aliases": [
            "ddocks"
        ],
        "enabled": true,
        "keyEmote": "ddockK",
        "pingRole": null,
        "headcountEmote": "ddock",
        "headcountOnAfk": true,
        "isSplit": false,
        "vialReact": false,
        "twoPhase": false,
        "startDelay": 5000,
        "vcCap": 45,
        "timeLimit": 300,
        "keyCount": 3,
        "color": "#000000",
        "isExalt": false,
        "reacts": [
            "UTCloakofthePlanewalker",
            "Warrior",
            "Paladin",
            "Knight",
            "Bard",
            "Priest"
        ],
        "earlyLocationCost": 15,
        "earlyLocationReacts": []
    },
    "woodland": {
        "runType": "Woodland Labyrinth",
        "runName": "Woodland Labyrinth",
        "aliases": [
            "wlab"
        ],
        "enabled": true,
        "keyEmote": "wlandK",
        "pingRole": null,
        "headcountEmote": "wland",
        "headcountOnAfk": true,
        "isSplit": false,
        "vialReact": false,
        "twoPhase": false,
        "startDelay": 5000,
        "vcCap": 45,
        "timeLimit": 300,
        "keyCount": 3,
        "color": "#00ff00",
        "isExalt": false,
        "reacts": [
            "UTCloakofthePlanewalker",
            "Collo",
            "Warrior",
            "Paladin",
            "Knight",
            "Bard",
            "Trickster",
            "Priest"
        ],
        "earlyLocationCost": 15,
        "earlyLocationReacts": []
    },
    "crawlingdepths": {
        "runType": "Crawling Depths",
        "runName": "Crawling Depths",
        "aliases": [
            "cdepths"
        ],
        "enabled": true,
        "keyEmote": "cdepthsK",
        "pingRole": null,
        "headcountEmote": "cdepths",
        "headcountOnAfk": true,
        "isSplit": false,
        "vialReact": false,
        "twoPhase": false,
        "startDelay": 5000,
        "vcCap": 45,
        "timeLimit": 300,
        "keyCount": 3,
        "color": "#ff00ff",
        "isExalt": false,
        "reacts": [
            "UTCloakofthePlanewalker",
            "Collo",
            "Warrior",
            "Paladin",
            "Knight",
            "Bard",
            "Trickster",
            "Priest"
        ],
        "earlyLocationCost": 15,
        "earlyLocationReacts": []
    },
    "oceantrench": {
        "runType": "Ocean Trench",
        "runName": "Ocean Trench",
        "aliases": [
            "ot"
        ],
        "enabled": true,
        "keyEmote": "otK",
        "pingRole": null,
        "headcountEmote": "ot",
        "headcountOnAfk": true,
        "isSplit": false,
        "vialReact": false,
        "twoPhase": false,
        "startDelay": 5000,
        "vcCap": 45,
        "timeLimit": 300,
        "keyCount": 3,
        "color": "#ff00ff",
        "isExalt": false,
        "reacts": [
            "UTCloakofthePlanewalker",
            "Warrior",
            "Paladin",
            "Knight",
            "Bard",
            "Trickster",
            "Priest"
        ],
        "earlyLocationCost": 15,
        "earlyLocationReacts": []
    },
    "icecave": {
        "runType": "Ice Cave",
        "runName": "Ice Cave",
        "aliases": [
            "cave"
        ],
        "enabled": true,
        "keyEmote": "caveK",
        "pingRole": null,
        "headcountEmote": "cave",
        "headcountOnAfk": true,
        "isSplit": false,
        "vialReact": false,
        "twoPhase": false,
        "startDelay": 5000,
        "vcCap": 45,
        "timeLimit": 300,
        "keyCount": 3,
        "color": "#0000ff",
        "isExalt": false,
        "reacts": [
            "Collo",
            "Warrior",
            "Paladin",
            "Knight",
            "Bard",
            "Trickster",
            "Priest"
        ],
        "earlyLocationCost": 15,
        "earlyLocationReacts": []
    },
    "tomb": {
        "runType": "Tomb of Ancients",
        "runName": "Tomb of Ancients",
        "aliases": [],
        "enabled": true,
        "keyEmote": "tombK",
        "pingRole": null,
        "headcountEmote": "tomb",
        "headcountOnAfk": true,
        "isSplit": false,
        "vialReact": false,
        "twoPhase": false,
        "startDelay": 5000,
        "vcCap": 45,
        "timeLimit": 300,
        "keyCount": 3,
        "color": "#ffff00",
        "isExalt": false,
        "reacts": [
            "UTCloakofthePlanewalker",
            "Collo",
            "Curse",
            "Expose",
            "Warrior",
            "Paladin",
            "Knight",
            "Bard",
            "Trickster",
            "Priest"
        ],
        "earlyLocationCost": 15,
        "earlyLocationReacts": []
    },
    "fungal": {
        "runType": "Fungal Cavern",
        "runName": "Fungal Cavern",
        "aliases": [
            "fc"
        ],
        "enabled": true,
        "keyEmote": "fungalK",
        "pingRole": null,
        "headcountEmote": "fungal",
        "headcountOnAfk": true,
        "isSplit": false,
        "vialReact": false,
        "twoPhase": false,
        "startDelay": 5000,
        "vcCap": 45,
        "timeLimit": 300,
        "keyCount": 3,
        "color": "#0ba6ee",
        "isExalt": true,
        "reacts": [
            "UTCloakofthePlanewalker",
            "UTMarbleSeal",
            "Collo",
            "Ogmur",
            "Slow",
            "daze",
            "Curse",
            "Expose",
            "Warrior",
            "Paladin",
            "Knight",
            "Bard",
            "Trickster",
            "Priest"
        ],
        "keyPopPoints": 5,
        "earlyLocationCost": 15,
        "earlyLocationReacts": []
    },
    "Exaltedfungal": {
        "runType": "Exalted Fungal Cavern",
        "runName": "Exalted Fungal Cavern",
        "aliases": [
            "efc",
            "efun",
            "efungal",
            "exaltedf",
            "exaltedfungal"
        ],
        "enabled": true,
        "keyEmote": "fungalK",
        "pingRole": null,
        "headcountEmote": "fungal",
        "headcountOnAfk": true,
        "isSplit": false,
        "vialReact": false,
        "twoPhase": false,
        "startDelay": 5000,
        "vcCap": 45,
        "timeLimit": 300,
        "keyCount": 3,
        "color": "#0ba6ee",
        "isExalt": true,
        "reacts": [
            "UTCloakofthePlanewalker",
            "UTMarbleSeal",
            "Collo",
            "Ogmur",
            "Slow",
            "daze",
            "Curse",
            "Expose",
            "Warrior",
            "Paladin",
            "Knight",
            "Bard",
            "Trickster",
            "Priest"
        ],
        "keyPopPoints": 5,
        "earlyLocationCost": 15,
        "earlyLocationReacts": []
    },
    "nest": {
        "runType": "Nest",
        "runName": "Nest",
        "aliases": ["n"],
        "enabled": true,
        "keyEmote": "nestK",
        "pingRole": null,
        "headcountEmote": "nest",
        "headcountOnAfk": true,
        "isSplit": false,
        "vialReact": false,
        "twoPhase": false,
        "startDelay": 5000,
        "vcCap": 45,
        "timeLimit": 300,
        "keyCount": 3,
        "color": "#ff00ff",
        "isExalt": true,
        "reacts": [
            "Collo",
            "tomeOfTheMushroomTribesFungal",
            "Slow",
            "daze",
            "Curse",
            "Expose",
            "Warrior",
            "Paladin",
            "Bard",
            "Trickster",
            "Priest"
        ],
        "keyPopPoints": 5,
        "earlyLocationCost": 15,
        "earlyLocationReacts": []
    },
    "Exaltednest": {
        "runType": "Exalted Nest",
        "runName": "Exalted Nest",
        "aliases": [
            "en",
            "enest",
            "exaltednest"
        ],
        "enabled": true,
        "keyEmote": "nestK",
        "pingRole": null,
        "headcountEmote": "nest",
        "headcountOnAfk": true,
        "isSplit": false,
        "vialReact": false,
        "twoPhase": false,
        "startDelay": 5000,
        "vcCap": 45,
        "timeLimit": 300,
        "keyCount": 3,
        "color": "#ff00ff",
        "isExalt": true,
        "reacts": [
            "Collo",
            "tomeOfTheMushroomTribesFungal",
            "Slow",
            "daze",
            "Curse",
            "Expose",
            "Warrior",
            "Paladin",
            "Bard",
            "Trickster",
            "Priest"
        ],
        "keyPopPoints": 5,
        "earlyLocationCost": 15,
        "earlyLocationReacts": []
    },
    "fullskipnest": {
        "runType": "Full-skip Nest",
        "runName": "Full-skip Nest",
        "aliases": [
            "fsnest"
        ],
        "enabled": true,
        "keyEmote": "nestK",
        "pingRole": null,
        "headcountEmote": "nest",
        "headcountOnAfk": true,
        "isSplit": false,
        "vialReact": false,
        "twoPhase": false,
        "startDelay": 5000,
        "vcCap": 45,
        "timeLimit": 300,
        "keyCount": 3,
        "color": "#ff00ff",
        "isExalt": true,
        "reacts": [
            "Collo",
            "tomeOfTheMushroomTribesFungal",
            "STBrainoftheGolem",
            "Mystic",
            "Slow",
            "daze",
            "Curse",
            "Expose",
            "Warrior",
            "Paladin",
            "Knight",
            "Bard",
            "Trickster",
            "Priest"
        ],
        "keyPopPoints": 5,
        "earlyLocationCost": 15,
        "earlyLocationReacts": []
    },
    "Exaltedfullskipnest": {
        "runType": "Exalted Full-skip Nest",
        "runName": "Exalted Full-skip Nest",
        "aliases": [
            "efn",
            "efsn",
            "efsnest"
        ],
        "enabled": true,
        "keyEmote": "nestK",
        "pingRole": null,
        "headcountEmote": "nest",
        "headcountOnAfk": true,
        "isSplit": false,
        "vialReact": false,
        "twoPhase": false,
        "startDelay": 5000,
        "vcCap": 45,
        "timeLimit": 300,
        "keyCount": 3,
        "color": "#ff00ff",
        "isExalt": true,
        "reacts": [
            "Collo",
            "tomeOfTheMushroomTribesFungal",
            "STBrainoftheGolem",
            "Mystic",
            "Slow",
            "daze",
            "Curse",
            "Expose",
            "Warrior",
            "Paladin",
            "Knight",
            "Bard",
            "Trickster",
            "Priest"
        ],
        "keyPopPoints": 5,
        "earlyLocationCost": 15,
        "earlyLocationReacts": []
    },
    "shatters": {
        "runType": "Shatters",
        "runName": "Shatters",
        "aliases": [
            "shatts"
        ],
        "enabled": true,
        "keyEmote": "shattersKey",
        "headcountEmote": "shatters",
        "headcountOnAfk": true,
        "color": "#015c21",
        "rushers": true,
        "stun": true,
        "ogmur": true,
        "fungal": false,
        "mseal": false,
        "brain": false,
        "stasis": true,
        "parylize": false,
        "slow": false,
        "daze": false,
        "curse": true,
        "expose": true,
        "warrior": true,
        "paladin": true,
        "knight": true,
        "bard": true,
        "trickster": true,
        "priest": true,
        "keyCount": 1,
        "isExalt": true,
        "reacts": [
            "UTCloakofthePlanewalker",
            "Collo",
            "Ogmur",
            "Mystic",
            "Curse",
            "Expose",
            "Warrior",
            "Paladin",
            "Knight",
            "Bard",
            "Trickster",
            "Priest"
        ],
        "keyPopPoints": 5,
        "earlyLocationCost": 15,
        "earlyLocationReacts": []
    },
    "Exaltedshatters": {
        "runType": "Exalted Shatters",
        "runName": "Exalted Shatters",
        "aliases": [
            "es",
            "eshatts",
            "exaltedshatts"
        ],
        "enabled": true,
        "keyEmote": "shattersKey",
        "pingRole": null,
        "headcountEmote": "shatters",
        "headcountOnAfk": true,
        "isSplit": false,
        "vialReact": false,
        "twoPhase": false,
        "startDelay": 5000,
        "vcCap": 45,
        "timeLimit": 300,
        "keyCount": 1,
        "color": "#015c21",
        "isExalt": true,
        "reacts": [
            "UTCloakofthePlanewalker",
            "Collo",
            "Ogmur",
            "Mystic",
            "Curse",
            "Expose",
            "Warrior",
            "Paladin",
            "Knight",
            "Bard",
            "Trickster",
            "Priest"
        ],
        "keyPopPoints": 5,
        "earlyLocationCost": 15,
        "earlyLocationReacts": []
    },
    "shaitan": {
        "runType": "Shaitans",
        "runName": "Shaitans",
        "aliases": [],
        "enabled": true,
        "keyEmote": "shaitanK",
        "pingRole": null,
        "headcountEmote": "shaitan",
        "headcountOnAfk": true,
        "isSplit": false,
        "vialReact": false,
        "twoPhase": false,
        "startDelay": 5000,
        "vcCap": 25,
        "timeLimit": 300,
        "keyCount": 3,
        "color": "#ff0000",
        "isExalt": false,
        "reacts": [
            "Ogmur",
            "Curse",
            "Expose",
            "Warrior",
            "Paladin",
            "Knight",
            "Bard",
            "Priest"
        ],
        "earlyLocationCost": 15,
        "earlyLocationReacts": []
    },
    "encore": {
        "runType": "Encore",
        "runName": "Encore",
        "aliases": [],
        "enabled": true,
        "keyEmote": "encoreK",
        "pingRole": null,
        "headcountEmote": "encore",
        "headcountOnAfk": true,
        "isSplit": false,
        "vialReact": false,
        "twoPhase": false,
        "startDelay": 5000,
        "vcCap": 25,
        "timeLimit": 300,
        "keyCount": 3,
        "color": "#000000",
        "isExalt": false,
        "reacts": [
            "Collo",
            "Slow",
            "Mystic",
            "Warrior",
            "Paladin",
            "Knight",
            "Bard",
            "Trickster",
            "Priest"
        ],
        "earlyLocationCost": 15,
        "earlyLocationReacts": []
    },
    "reef": {
        "runType": "Cnidarian Reef",
        "runName": "Cnidarian Reef",
        "aliases": [],
        "enabled": true,
        "keyEmote": "reefK",
        "pingRole": null,
        "headcountEmote": "reef",
        "headcountOnAfk": true,
        "isSplit": false,
        "vialReact": false,
        "twoPhase": false,
        "startDelay": 5000,
        "vcCap": 25,
        "timeLimit": 300,
        "keyCount": 3,
        "color": "#ffffff",
        "isExalt": false,
        "reacts": [
            "Slow",
            "daze",
            "Mystic",
            "Warrior",
            "Paladin",
            "Knight",
            "Bard",
            "Priest"
        ],
        "earlyLocationCost": 15,
        "earlyLocationReacts": []
    },
    "thicket": {
        "runType": "Thicket",
        "runName": "Thicket",
        "aliases": [],
        "enabled": true,
        "keyEmote": "thicketK",
        "pingRole": null,
        "headcountEmote": "thicket",
        "headcountOnAfk": true,
        "isSplit": false,
        "vialReact": false,
        "twoPhase": false,
        "startDelay": 5000,
        "vcCap": 25,
        "timeLimit": 300,
        "keyCount": 3,
        "color": "#00ff00",
        "isExalt": false,
        "reacts": [
            "Collo",
            "tomeOfTheMushroomTribesFungal",
            "Slow",
            "Warrior",
            "Paladin",
            "Knight",
            "Bard",
            "Trickster",
            "Priest"
        ],
        "earlyLocationCost": 15,
        "earlyLocationReacts": []
    },
    "hudl": {
        "runType": "Heroic Undead Lair",
        "runName": "Heroic Undead Lair",
        "aliases": [],
        "enabled": true,
        "keyEmote": "hudlK",
        "pingRole": null,
        "headcountEmote": "hudl2",
        "headcountOnAfk": true,
        "isSplit": false,
        "vialReact": false,
        "twoPhase": false,
        "startDelay": 5000,
        "vcCap": 15,
        "timeLimit": 300,
        "keyCount": 3,
        "color": "#000000",
        "isExalt": false,
        "reacts": [
            "daze",
            "Warrior",
            "Paladin",
            "Knight",
            "Bard",
            "Priest"
        ],
        "earlyLocationCost": 15,
        "earlyLocationReacts": []
    },
    "habyss": {
        "runType": "Heroic Abyss of Demons",
        "runName": "Heroic Abyss of Demons",
        "aliases": [],
        "enabled": true,
        "keyEmote": "habyK",
        "pingRole": null,
        "headcountEmote": "haby",
        "headcountOnAfk": true,
        "isSplit": false,
        "vialReact": false,
        "twoPhase": false,
        "startDelay": 5000,
        "vcCap": 15,
        "timeLimit": 300,
        "keyCount": 3,
        "color": "#000000",
        "isExalt": false,
        "reacts": [
            "daze",
            "Warrior",
            "Paladin",
            "Knight",
            "Bard",
            "Priest"
        ],
        "earlyLocationCost": 15,
        "earlyLocationReacts": []
    },
    "battlenexus": {
        "runType": "Battle Nexus",
        "runName": "Battle Nexus",
        "aliases": [
            "bnex"
        ],
        "enabled": true,
        "keyEmote": "bnexK",
        "pingRole": null,
        "headcountEmote": "bnex",
        "headcountOnAfk": true,
        "isSplit": false,
        "vialReact": false,
        "twoPhase": false,
        "startDelay": 5000,
        "vcCap": 45,
        "timeLimit": 300,
        "keyCount": 3,
        "color": "#000000",
        "isExalt": false,
        "reacts": [
            "Warrior",
            "Paladin",
            "Knight",
            "Bard",
            "Trickster",
            "Priest"
        ],
        "earlyLocationCost": 15,
        "earlyLocationReacts": []
    },
    "bella": {
        "runType": "Belladonna's Garden",
        "runName": "Belladonna's Garden",
        "aliases": [],
        "enabled": true,
        "keyEmote": "bellaK",
        "pingRole": null,
        "headcountEmote": "bella",
        "headcountOnAfk": true,
        "isSplit": false,
        "vialReact": false,
        "twoPhase": false,
        "startDelay": 5000,
        "vcCap": 45,
        "timeLimit": 300,
        "keyCount": 3,
        "color": "#00ff00",
        "isExalt": false,
        "reacts": [
            "Warrior",
            "Paladin",
            "Knight",
            "Bard",
            "Priest"
        ],
        "earlyLocationCost": 15,
        "earlyLocationReacts": []
    },
    "icetomb": {
        "runType": "Ice Tomb",
        "runName": "Ice Tomb",
        "aliases": [],
        "enabled": true,
        "keyEmote": "itombK",
        "pingRole": null,
        "headcountEmote": "itomb",
        "headcountOnAfk": true,
        "isSplit": false,
        "vialReact": false,
        "twoPhase": true,
        "startDelay": 5000,
        "vcCap": 45,
        "timeLimit": 300,
        "keyCount": 3,
        "color": "#fefefe",
        "isExalt": false,
        "reacts": [
            "Collo",
            "Slow",
            "Curse",
            "Expose",
            "Warrior",
            "Paladin",
            "Knight",
            "Bard",
            "Priest"
        ],
        "earlyLocationCost": 15,
        "earlyLocationReacts": []
    },
    "caveofathousandtreasures": {
        "runType": "Cave of a Thousand Treasures",
        "runName": "Cave of a Thousand Treasures",
        "aliases": [
            "tcave"
        ],
        "enabled": true,
        "keyEmote": "ttK",
        "pingRole": null,
        "headcountEmote": "tt",
        "headcountOnAfk": true,
        "isSplit": false,
        "vialReact": false,
        "twoPhase": false,
        "startDelay": 5000,
        "vcCap": 45,
        "timeLimit": 300,
        "keyCount": 3,
        "color": "#000000",
        "isExalt": false,
        "reacts": [
            "UTCloakofthePlanewalker",
            "Warrior",
            "Paladin",
            "Knight",
            "Bard",
            "Trickster",
            "Priest"
        ],
        "earlyLocationCost": 15,
        "earlyLocationReacts": []
    },
    "puppet": {
        "runType": "Puppet Theatre",
        "runName": "Puppet Theatre",
        "aliases": [
            "pup"
        ],
        "enabled": true,
        "keyEmote": "puppetK",
        "pingRole": null,
        "headcountEmote": "pup",
        "headcountOnAfk": true,
        "isSplit": false,
        "vialReact": false,
        "twoPhase": false,
        "startDelay": 5000,
        "vcCap": 45,
        "timeLimit": 300,
        "keyCount": 3,
        "color": "#000000",
        "isExalt": false,
        "reacts": [
            "UTCloakofthePlanewalker",
            "Warrior",
            "Paladin",
            "Knight",
            "Bard",
            "Trickster",
            "Priest"
        ],
        "earlyLocationCost": 15,
        "earlyLocationReacts": []
    },
    "ruins": {
        "runType": "Ancient Ruins",
        "runName": "Ancient Ruins",
        "aliases": [],
        "enabled": true,
        "keyEmote": "ruinsK",
        "pingRole": null,
        "headcountEmote": "ruins",
        "headcountOnAfk": true,
        "isSplit": false,
        "vialReact": false,
        "twoPhase": false,
        "startDelay": 5000,
        "vcCap": 45,
        "timeLimit": 300,
        "keyCount": 3,
        "color": "#ffff00",
        "isExalt": false,
        "reacts": [
            "UTCloakofthePlanewalker",
            "Collo",
            "tomeOfTheMushroomTribesFungal",
            "UTMarbleSeal",
            "Ogmur",
            "Slow",
            "daze",
            "Curse",
            "Expose",
            "Warrior",
            "Paladin",
            "Knight",
            "Bard",
            "Priest"
        ],
        "earlyLocationCost": 15,
        "earlyLocationReacts": []
    },
    "htt": {
        "runType": "High Tech Terror",
        "runName": "High Tech Terror",
        "aliases": [],
        "enabled": true,
        "keyEmote": "httK",
        "pingRole": null,
        "headcountEmote": "htt",
        "headcountOnAfk": true,
        "isSplit": false,
        "vialReact": false,
        "twoPhase": false,
        "startDelay": 5000,
        "vcCap": 25,
        "timeLimit": 300,
        "keyCount": 3,
        "color": "#ff00ff",
        "isExalt": false,
        "reacts": [
            "Collo",
            "UTMarbleSeal",
            "Ogmur",
            "Curse",
            "Expose",
            "Warrior",
            "Paladin",
            "Knight",
            "Bard",
            "Trickster",
            "Priest"
        ],
        "earlyLocationCost": 15,
        "earlyLocationReacts": []
    },
    "random": {
        "runType": "Random",
        "runName": "Random",
        "aliases": [],
        "enabled": true,
        "keyEmote": "oryx",
        "pingRole": null,
        "headcountEmote": "pcave",
        "headcountOnAfk": true,
        "isSplit": false,
        "vialReact": false,
        "twoPhase": false,
        "startDelay": 5000,
        "vcCap": 45,
        "timeLimit": 300,
        "keyCount": 3,
        "color": "#fefefe",
        "isExalt": false,
        "reacts": [
            "UTCloakofthePlanewalker",
            "Collo",
            "tomeOfTheMushroomTribesFungal",
            "UTMarbleSeal",
            "STBrainoftheGolem",
            "Ogmur",
            "Slow",
            "daze",
            "Curse",
            "Expose",
            "Mystic",
            "Warrior",
            "Paladin",
            "Knight",
            "Bard",
            "Trickster",
            "Priest"
        ],
        "earlyLocationCost": 15,
        "earlyLocationReacts": []
    },
    "exalts": {
        "runType": "exalts",
        "runName": "exalts",
        "aliases": [
            "ex",
            "exaltations",
            "exaltation"
        ],
        "enabled": true,
        "pingRole": null,
        "headcountOnAfk": true,
        "isSplit": false,
        "vialReact": false,
        "twoPhase": false,
        "startDelay": 5000,
        "vcCap": 45,
        "timeLimit": 300,
        "keyCount": 3,
        "color": "#fefefe",
        "isExalt": false,
        "reacts": [
            "void",
            "VialOfPureDarkness",
            "cultist",
            "UTCloakofthePlanewalker",
            "fungal",
            "nest",
            "steamworksPortal",
            "shatters",
            "mv",
            "hallsK",
            "fungalK",
            "nestK",
            "shattersKey",
            "steamworksKey",
            "mvK"
        ],
        "embed": {
            "headcountDescription": "React with any Dungeon Icon if you plan on joining\nReact with any Dungeon Key if you plan on bringing any key",
            "color": "#fefefe"
        },
        "earlyLocationCost": 15,
        "earlyLocationReacts": []
    },
    "steamworks": {
        "runType": "Kogbold Steamworks",
        "runName": "Kogbold Steamworks",
        "aliases": [
            "k",
            "steamworks",
            "sw",
            "ksw"
        ],
        "enabled": true,
        "keyEmote": "steamworksKey",
        "pingRole": "steamworksping",
        "headcountEmote": "steamworksPortal",
        "headcountOnAfk": false,
        "runLogName": "steamworkRuns",
        "isSplit": false,
        "vialReact": false,
        "twoPhase": true,
        "startDelay": 5000,
        "vcCap": 45,
        "timeLimit": 300,
        "keyCount": 1,
        "thumbnail": "https://i.imgur.com/wSoAGoR.png",
        "color": "#7a7a7a",
        "isExalt": true,
        "earlyLocationReacts": [
            {
                "emote": "armor",
                "pointsGiven": 0,
                "limit": 1,
                "shortName": "High Defense Dragger",
                "confirmationMessage": "**__REQUIRED__**\n- You must know how to drag the boss around in the Enforcer: Minefield phase (Check GIF Below).\n- You are recommended to have **80+ Defense** on your character.",
                "confirmationMedia": "https://cdn.discordapp.com/attachments/230500411835023362/1059570168558256178/how_to_drag_minefields.gif",
                "noConfirm": false,
                "noLocation": false
            },
            {
                "emote": "UTMarbleSeal",
                "pointsGiven": 0,
                "limit": 1,
                "shortName": "Marble Seal",
                "noConfirm": false,
                "noLocation": false
            },
            {
                "emote": "tomeOfTheMushroomTribesFungal",
                "pointsGiven": 0,
                "limit": 2,
                "shortName": "Fungal Tome",
                "noConfirm": false,
                "noLocation": false
            },
            {
                "emote": "Ogmur",
                "pointsGiven": 0,
                "limit": 1,
                "shortName": "Armor Break",
                "noConfirm": false,
                "noLocation": false
            },
            {
                "emote": "Expose",
                "pointsGiven": 0,
                "limit": 1,
                "shortName": "Expose",
                "noConfirm": false,
                "noLocation": false
            },
            {
                "emote": "Slow",
                "pointsGiven": 0,
                "limit": 2,
                "shortName": "Slow",
                "noConfirm": false,
                "noLocation": false
            },
            {
                "emote": "daze",
                "pointsGiven": 0,
                "limit": 1,
                "shortName": "Daze",
                "noConfirm": false,
                "noLocation": false
            },
            {
                "emote": "Trickster",
                "pointsGiven": 0,
                "limit": 1,
                "shortName": "Trickster",
                "noConfirm": false,
                "noLocation": false
            }
        ],
        "reacts": [
            "Curse",
            "Warrior",
            "Paladin",
            "Knight",
            "Bard"
        ],
        "earlyLocationCost": 15
    },
    "Exaltedsteamworks": {
        "runType": "Exalted Kogbold Steamworks",
        "runName": "Exalted Kogbold Steamworks",
        "aliases": [
            "ek",
            "esteamworks",
            "esw",
            "eksw",
            "exaltedk",
            "exaltedkogbold",
            "exaltedsteamwork",
            "exaltedsteamworks",
            "exaltedkogboldsteamwork",
            "exaltedkogboldsteamworks"
        ],
        "enabled": true,
        "keyEmote": "steamworksKey",
        "pingRole": "steamworksping",
        "headcountEmote": "steamworksPortal",
        "headcountOnAfk": false,
        "runLogName": "steamworkRuns",
        "isSplit": false,
        "vialReact": false,
        "twoPhase": true,
        "startDelay": 5000,
        "vcCap": 45,
        "timeLimit": 300,
        "keyCount": 1,
        "thumbnail": "https://i.imgur.com/wSoAGoR.png",
        "color": "#7a7a7a",
        "isExalt": true,
        "earlyLocationReacts": [
            {
                "emote": "armor",
                "pointsGiven": 0,
                "limit": 1,
                "shortName": "High Defense Dragger",
                "confirmationMessage": "**__REQUIRED__**\n- You must know how to drag the boss around in the Enforcer: Minefield phase (Check GIF Below).\n- You are recommended to have **80+ Defense** on your character.",
                "confirmationMedia": "https://cdn.discordapp.com/attachments/230500411835023362/1059570168558256178/how_to_drag_minefields.gif",
                "noConfirm": false,
                "noLocation": false
            },
            {
                "emote": "UTMarbleSeal",
                "pointsGiven": 0,
                "limit": 1,
                "shortName": "Marble Seal",
                "noConfirm": false,
                "noLocation": false
            },
            {
                "emote": "tomeOfTheMushroomTribesFungal",
                "pointsGiven": 0,
                "limit": 2,
                "shortName": "Fungal Tome",
                "noConfirm": false,
                "noLocation": false
            },
            {
                "emote": "Ogmur",
                "pointsGiven": 0,
                "limit": 1,
                "shortName": "Armor Break",
                "noConfirm": false,
                "noLocation": false
            },
            {
                "emote": "Expose",
                "pointsGiven": 0,
                "limit": 1,
                "shortName": "Expose",
                "noConfirm": false,
                "noLocation": false
            },
            {
                "emote": "Slow",
                "pointsGiven": 0,
                "limit": 2,
                "shortName": "Slow",
                "noConfirm": false,
                "noLocation": false
            },
            {
                "emote": "daze",
                "pointsGiven": 0,
                "limit": 1,
                "shortName": "Daze",
                "noConfirm": false,
                "noLocation": false
            },
            {
                "emote": "Trickster",
                "pointsGiven": 0,
                "limit": 1,
                "shortName": "Trickster",
                "noConfirm": false,
                "noLocation": false
            }
        ],
        "reacts": [
            "Curse",
            "Warrior",
            "Paladin",
            "Knight",
            "Bard"
        ],
        "earlyLocationCost": 15
    },
    "moonlight": {
        "runType": "Moonlight Village",
        "runName": "Moonlight Village",
        "aliases": [
            "mv",
            "moonv",
            "moonlightv",
            "moonlightvillage"
        ],
        "enabled": true,
        "keyEmote": "mvK",
        "pingRole": "moonlightping",
        "headcountEmote": "mv",
        "headcountOnAfk": false,
        "runLogName": "moonlightRuns",
        "isSplit": false,
        "vialReact": false,
        "twoPhase": true,
        "startDelay": 5000,
        "vcCap": 45,
        "timeLimit": 300,
        "keyCount": 1,
        "thumbnail": "https://cdn.discordapp.com/emojis/1090178399252783104.webp",
        "color": "#7a7a7a",
        "isExalt": true,
        "earlyLocationReacts": [
            {
                "emote": "UTMarbleSeal",
                "pointsGiven": 0,
                "limit": 1,
                "shortName": "Marble Seal",
                "noConfirm": false,
                "noLocation": false
            },
            {
                "emote": "tomeOfTheMushroomTribesFungal",
                "pointsGiven": 0,
                "limit": 2,
                "shortName": "Fungal Tome",
                "noConfirm": false,
                "noLocation": false
            }
        ],
        "reacts": [
            "Curse",
            "Warrior",
            "Paladin",
            "Knight",
            "Bard"
        ],
        "earlyLocationCost": 15
    },
    "Exaltedmoonlight": {
        "runType": "Exalted Moonlight Village",
        "runName": "Exalted Moonlight Village",
        "aliases": [
            "emv",
            "emoonv",
            "emoonlight",
            "emoonlightv",
            "emoonlightvillage",
            "exaltedmv",
            "exaltedmoonv",
            "exaltedmoonlightv",
            "exaltedmoonlightvillage"
        ],
        "enabled": true,
        "keyEmote": "mvK",
        "pingRole": "moonlightping",
        "headcountEmote": "mv",
        "headcountOnAfk": false,
        "runLogName": "moonlightRuns",
        "isSplit": false,
        "vialReact": false,
        "twoPhase": true,
        "startDelay": 5000,
        "vcCap": 45,
        "timeLimit": 300,
        "keyCount": 1,
        "color": "#7a7a7a",
        "thumbnail": "https://cdn.discordapp.com/emojis/1090178399252783104.webp",
        "isExalt": true,
        "earlyLocationReacts": [
            {
                "emote": "UTMarbleSeal",
                "pointsGiven": 0,
                "limit": 1,
                "shortName": "Marble Seal",
                "noConfirm": false,
                "noLocation": false
            },
            {
                "emote": "tomeOfTheMushroomTribesFungal",
                "pointsGiven": 0,
                "limit": 2,
                "shortName": "Fungal Tome",
                "noConfirm": false,
                "noLocation": false
            }
        ],
        "reacts": [
            "Curse",
            "Warrior",
            "Paladin",
            "Knight",
            "Bard"
        ],
        "earlyLocationCost": 15
    },
    "701483950559985705": {
        "fungal": {
            "name": "Fungal Cavern",
            "runType": "Fungal Cavern",
            "runName": "Fungal Cavern",
            "aliases": [
                "fc",
                "fungal"
            ],
            "enabled": true,
            "keyEmote": "fungalK",
            "headcountEmote": "fungal",
            "headcountOnAfk": true,
            "runLogName": "fungalRuns",
            "thumbnail": "https://i.imgur.com/5DfG6i5.png",
            "color": "#0ba6ee",
            "keyCount": 3,
            "keyPopPoints": 5,
            "earlyLocationCost": 15,
            "vcCap" : 45,
            "twoPhase": true,
            "pingRole": "fungalReact",
            "isExalt": true,
            "reacts": [
                "daze",
                "Curse",
                "Expose",
                "Warrior",
                "Paladin",
                "Knight",
                "Bard",
                "Trickster",
                "Priest"
            ],
            "earlyLocationReacts": [
                {
                    "emote": "UTMarbleSeal",
                    "pointsGiven": 0,
                    "limit": 1,
                    "shortName": "Marble Seal",
                    "noConfirm": false,
                    "noLocation": false
                },
                {
                    "emote": "tomeOfTheMushroomTribesFungal",
                    "pointsGiven": 0,
                    "limit": 1,
                    "shortName": "Fungal Tome",
                    "noConfirm": false,
                    "noLocation": true
                },
                {
                    "emote": "daze",
                    "pointsGiven": 0,
                    "limit": 1,
                    "shortName": "Daze",
                    "noConfirm": false,
                    "noLocation": false
                },
                {
                    "emote": "Slow",
                    "pointsGiven": 0,
                    "limit": 2,
                    "shortName": "Slow",
                    "noConfirm": false,
                    "noLocation": false
                },
                {
                    "emote": "Collo",
                    "pointsGiven": 0,
                    "limit": 2,
                    "shortName": "Stun",
                    "noConfirm": false,
                    "noLocation": false
                },
                {
                    "emote": "Ogmur",
                    "pointsGiven": 1,
                    "limit": 1,
                    "shortName": "Armor Break",
                    "noConfirm": false,
                    "noLocation": false
                }
            ]
        },
        "Exaltedfungal": {
            "name": "Exalted Fungal Cavern",
            "runType": "Exalted Fungal Cavern",
            "runName": "Exalted Fungal Cavern",
            "aliases": [
                "efc",
                "efun",
                "efungal",
                "exaltedf",
                "exaltedfungal"
            ],
            "enabled": true,
            "keyEmote": "fungalK",
            "headcountEmote": "fungal",
            "headcountOnAfk": true,
            "runLogName": "fungalRuns",
            "thumbnail": "https://i.imgur.com/5DfG6i5.png",
            "color": "#0ba6ee",
            "twoPhase": true,
            "keyCount": 3,
            "keyPopPoints": 5,
            "earlyLocationCost": 15,
            "vcCap": 45,
            "pingRole": "fungalReact",
            "isExalt": true,
            "isExalted": true,
            "reacts": [
                "daze",
                "Curse",
                "Expose",
                "Warrior",
                "Paladin",
                "Knight",
                "Bard",
                "Trickster",
                "Priest"
            ],
            "earlyLocationReacts": [
                {
                    "emote": "UTMarbleSeal",
                    "pointsGiven": 0,
                    "limit": 1,
                    "shortName": "Marble Seal",
                    "noConfirm": false,
                    "noLocation": false
                },
                {
                    "emote": "tomeOfTheMushroomTribesFungal",
                    "pointsGiven": 0,
                    "limit": 1,
                    "shortName": "Fungal Tome",
                    "noConfirm": false,
                    "noLocation": true
                },
                {
                    "emote": "daze",
                    "pointsGiven": 0,
                    "limit": 1,
                    "shortName": "Daze",
                    "noConfirm": false,
                    "noLocation": false
                },
                {
                    "emote": "Slow",
                    "pointsGiven": 0,
                    "limit": 2,
                    "shortName": "Slow",
                    "noConfirm": false,
                    "noLocation": false
                },
                {
                    "emote": "Collo",
                    "pointsGiven": 0,
                    "limit": 2,
                    "shortName": "Stun",
                    "noConfirm": false,
                    "noLocation": false
                },
                {
                    "emote": "Ogmur",
                    "pointsGiven": 1,
                    "limit": 1,
                    "shortName": "Armor Break",
                    "noConfirm": false,
                    "noLocation": false
                }
            ]
        },
        "nest": {
            "name": "Nest",
            "runType": "Nest",
            "runName": "Nest",
            "aliases": [],
            "enabled": true,
            "runLogName": "nestRuns",
            "keyEmote": "nestK",
            "headcountEmote": "nest",
            "headcountOnAfk": true,
            "thumbnail": "https://i.imgur.com/hUWc3IV.png",
            "color": "#ffd700",
            "twoPhase": true,
            "reacts": [
                "Curse",
                "Expose",
                "Warrior",
                "Paladin",
                "Knight",
                "Bard",
                "Trickster",
                "Priest"
            ],
            "keyCount": 3,
            "keyPopPoints": 5,
            "earlyLocationCost": 15,
            "vcCap" : 45,
            "pingRole": "nestReact",
            "isExalt": true,
            "earlyLocationReacts": [
                {
                    "emote": "UTMarbleSeal",
                    "pointsGiven": 0,
                    "limit": 1,
                    "shortName": "Marble Seal",
                    "noConfirm": false,
                    "noLocation": false
                },
                {
                    "emote": "Collo",
                    "pointsGiven": 0,
                    "limit": 2,
                    "shortName": "Stun",
                    "noConfirm": false,
                    "noLocation": true
                },
                {
                    "emote": "Slow",
                    "pointsGiven": 0,
                    "limit": 2,
                    "shortName": "Slow",
                    "noConfirm": false,
                    "noLocation": false
                },
                {
                    "emote": "Ogmur",
                    "pointsGiven": 1,
                    "limit": 1,
                    "shortName": "Armor Break",
                    "noConfirm": false,
                    "noLocation": false
                },
                {
                    "emote": "daze",
                    "pointsGiven": 0,
                    "limit": 1,
                    "shortName": "Daze",
                    "noConfirm": false,
                    "noLocation": false
                }
            ]
        },
        "Exaltednest": {
            "name": "Exalted Nest",
            "runType": "Exalted Nest",
            "runName": "Exalted Nest",
            "aliases": [
                "en",
                "enest",
                "exaltednest"
            ],
            "enabled": true,
            "runLogName": "nestRuns",
            "keyEmote": "nestK",
            "headcountEmote": "nest",
            "headcountOnAfk": true,
            "thumbnail": "https://i.imgur.com/hUWc3IV.png",
            "color": "#ffd700",
            "twoPhase": true,
            "keyCount": 3,
            "keyPopPoints": 5,
            "earlyLocationCost": 15,
            "vcCap": 45,
            "pingRole": "nestReact",
            "isExalt": true,
            "isExalted": true,
            "reacts": [
                "Curse",
                "Expose",
                "Warrior",
                "Paladin",
                "Knight",
                "Bard",
                "Trickster",
                "Priest"
            ],
            "earlyLocationReacts": [
                {
                    "emote": "UTMarbleSeal",
                    "pointsGiven": 0,
                    "limit": 1,
                    "shortName": "Marble Seal",
                    "noConfirm": false,
                    "noLocation": false
                },
                {
                    "emote": "Collo",
                    "pointsGiven": 0,
                    "limit": 2,
                    "shortName": "Stun",
                    "noConfirm": false,
                    "noLocation": true
                },
                {
                    "emote": "Slow",
                    "pointsGiven": 0,
                    "limit": 2,
                    "shortName": "Slow",
                    "noConfirm": false,
                    "noLocation": false
                },
                {
                    "emote": "Ogmur",
                    "pointsGiven": 1,
                    "limit": 1,
                    "shortName": "Armor Break",
                    "noConfirm": false,
                    "noLocation": false
                },
                {
                    "emote": "daze",
                    "pointsGiven": 0,
                    "limit": 1,
                    "shortName": "Daze",
                    "noConfirm": false,
                    "noLocation": false
                }
            ]
        },
        "fullskipnest": {
            "name": "Full-skip Nest",
            "runType": "Full-skip Nest",
            "runName": "Full-skip Nest",
            "aliases": [
                "fn",
                "fsnest"
            ],
            "enabled": true,
            "keyEmote": "nestK",
            "runLogName": "nestRuns",
            "headcountEmote": "nest",
            "headcountOnAfk": true,
            "thumbnail": "https://i.imgur.com/hUWc3IV.png",
            "color": "#ffd700",
            "expose": true,
            "twoPhase": true,
            "keyCount": 3,
            "keyPopPoints": 5,
            "earlyLocationCost": 15,
            "vcCap" : 45,
            "pingRole": "nestReact",
            "isExalt": true,
            "reacts": [
                "Curse",
                "Expose",
                "Warrior",
                "Paladin",
                "Knight",
                "Bard",
                "Trickster",
                "Priest"
            ],
            "earlyLocationReacts": [
                {
                    "emote": "UTMarbleSeal",
                    "pointsGiven": 0,
                    "limit": 1,
                    "shortName": "Marble Seal",
                    "noConfirm": false,
                    "noLocation": false
                },
                {
                    "emote": "Collo",
                    "pointsGiven": 0,
                    "limit": 2,
                    "shortName": "Stun",
                    "noConfirm": false,
                    "noLocation": true
                },
                {
                    "emote": "Slow",
                    "pointsGiven": 0,
                    "limit": 2,
                    "shortName": "Slow",
                    "noConfirm": false,
                    "noLocation": false
                },
                {
                    "emote": "Ogmur",
                    "pointsGiven": 1,
                    "limit": 1,
                    "shortName": "Armor Break",
                    "noConfirm": false,
                    "noLocation": false
                },
                {
                    "emote": "daze",
                    "pointsGiven": 0,
                    "limit": 1,
                    "shortName": "Daze",
                    "noConfirm": false,
                    "noLocation": false
                }
            ]
        },
        "Exaltedfullskipnest": {
            "name": "Exalted Full-skip Nest",
            "runType": "Exalted Full-skip Nest",
            "runName": "Exalted Full-skip Nest",
            "aliases": [
                "efn",
                "efsn",
                "efsnest"
            ],
            "enabled": true,
            "keyEmote": "nestK",
            "headcountEmote": "nest",
            "headcountOnAfk": true,
            "runLogName": "nestRuns",
            "thumbnail": "https://i.imgur.com/hUWc3IV.png",
            "color": "#ffd700",
            "reacts": [
                "Curse",
                "Expose",
                "Warrior",
                "Paladin",
                "Knight",
                "Bard",
                "Trickster",
                "Priest"
            ],
            "twoPhase": true,
            "keyCount": 3,
            "keyPopPoints": 5,
            "earlyLocationCost": 15,
            "vcCap": 45,
            "pingRole": "nestReact",
            "isExalt": true,
            "isExalted": true,
            "earlyLocationReacts": [
                {
                    "emote": "UTMarbleSeal",
                    "pointsGiven": 0,
                    "limit": 1,
                    "shortName": "Marble Seal",
                    "noConfirm": false,
                    "noLocation": false
                },
                {
                    "emote": "Collo",
                    "pointsGiven": 0,
                    "limit": 2,
                    "shortName": "Stun",
                    "noConfirm": false,
                    "noLocation": true
                },
                {
                    "emote": "Slow",
                    "pointsGiven": 0,
                    "limit": 2,
                    "shortName": "Slow",
                    "noConfirm": false,
                    "noLocation": false
                },
                {
                    "emote": "Ogmur",
                    "pointsGiven": 1,
                    "limit": 1,
                    "shortName": "Armor Break",
                    "noConfirm": false,
                    "noLocation": false
                },
                {
                    "emote": "daze",
                    "pointsGiven": 0,
                    "limit": 1,
                    "shortName": "Daze",
                    "noConfirm": false,
                    "noLocation": false
                }
            ]
        }
    },
    "realmClearing": {
        "runType": "Realm Clearing",
        "runName": "Realm Clearing",
        "aliases": [
            "realmclearing",
            "rc",
            "realmc",
            "rclear",
            "realmclear",
            "realmclears"
        ],
        "enabled": true,
        "partneredServerPing": true,
        "portalEmojiID": "723001215184535553",
        "portalEmote": ":pcave:723001215184535553",
        "partneredServerPingPriority": "eventstatus",
        "pingRole": "rcPing",
        "headcountEmote": "pcave",
        "headcountOnAfk": false,
        "isSplit": false,
        "vialReact": false,
        "twoPhase": true,
        "startDelay": 5000,
        "vcCap": 75,
        "timeLimit": 300,
        "keyCount": 1,
        "color": "#058891",
        "isExalt": false,
        "earlyLocationReacts": [],
        "reacts": [],
        "earlyLocationCost": 15
    },
    "efficientRealmClearing": {
        "runType": "Efficient Realm Clearing",
        "runName": "Efficient Realm Clearing",
        "aliases": [
            "erealmclearing",
            "erc",
            "erealmc",
            "erclear",
            "erealmclear",
            "erealmclears",
            "efficientrealmclearing",
            "efficientrc",
            "efficientrealmc",
            "efficientrclear",
            "efficientrealmclear",
            "efficientrealmclears"
        ],
        "enabled": true,
        "partneredServerPing": true,
        "portalEmojiID": "723001215184535553",
        "portalEmote": ":pcave:723001215184535553",
        "partneredServerPingPriority": "eventstatus",
        "pingRole": "rcPing",
        "headcountEmote": "pcave",
        "headcountOnAfk": false,
        "isSplit": false,
        "vialReact": false,
        "twoPhase": true,
        "startDelay": 5000,
        "vcCap": 75,
        "timeLimit": 300,
        "keyCount": 1,
        "color": "#058891",
        "isExalt": false,
        "earlyLocationReacts": [],
        "reacts": [],
        "earlyLocationCost": 15
    },
    "343704644712923138": {
        "fungal": {
            "name": "Fungal Cavern",
            "runType": "Fungal Cavern",
            "runName": "Fungal Cavern",
            "aliases": [
                "fc",
                "fungal"
            ],
            "enabled": true,
            "keyEmote": "fungalK",
            "headcountEmote": "fungal",
            "headcountOnAfk": true,
            "runLogName": "fungalRuns",
            "thumbnail": "https://i.imgur.com/5DfG6i5.png",
            "color": "#0ba6ee",
            "keyCount": 3,
            "keyPopPoints": 5,
            "earlyLocationCost": 15,
            "vcCap" : 45,
            "twoPhase": true,
            "pingRole": "fungalReact",
            "isExalt": true,
            "reacts": [
                "daze",
                "Curse",
                "Expose",
                "Warrior",
                "Paladin",
                "Knight",
                "Bard",
                "Trickster",
                "Priest"
            ],
            "earlyLocationReacts": [
                {
                    "emote": "UTMarbleSeal",
                    "pointsGiven": 0,
                    "limit": 1,
                    "shortName": "Marble Seal",
                    "noConfirm": false,
                    "noLocation": false
                },
                {
                    "emote": "tomeOfTheMushroomTribesFungal",
                    "pointsGiven": 0,
                    "limit": 1,
                    "shortName": "Fungal Tome",
                    "noConfirm": false,
                    "noLocation": true
                },
                {
                    "emote": "daze",
                    "pointsGiven": 0,
                    "limit": 1,
                    "shortName": "Daze",
                    "noConfirm": false,
                    "noLocation": false
                },
                {
                    "emote": "Slow",
                    "pointsGiven": 0,
                    "limit": 2,
                    "shortName": "Slow",
                    "noConfirm": false,
                    "noLocation": false
                },
                {
                    "emote": "Collo",
                    "pointsGiven": 0,
                    "limit": 2,
                    "shortName": "Stun",
                    "noConfirm": false,
                    "noLocation": false
                },
                {
                    "emote": "Ogmur",
                    "pointsGiven": 1,
                    "limit": 1,
                    "shortName": "Armor Break",
                    "noConfirm": false,
                    "noLocation": false
                }
            ]
        },
        "Exaltedfungal": {
            "name": "Exalted Fungal Cavern",
            "runType": "Exalted Fungal Cavern",
            "runName": "Exalted Fungal Cavern",
            "aliases": [
                "efc",
                "efun",
                "efungal",
                "exaltedf",
                "exaltedfungal"
            ],
            "enabled": true,
            "keyEmote": "fungalK",
            "headcountEmote": "fungal",
            "headcountOnAfk": true,
            "runLogName": "fungalRuns",
            "thumbnail": "https://i.imgur.com/5DfG6i5.png",
            "color": "#0ba6ee",
            "twoPhase": true,
            "keyCount": 3,
            "keyPopPoints": 5,
            "earlyLocationCost": 15,
            "vcCap": 45,
            "pingRole": "fungalReact",
            "isExalt": true,
            "isExalted": true,
            "reacts": [
                "daze",
                "Curse",
                "Expose",
                "Warrior",
                "Paladin",
                "Knight",
                "Bard",
                "Trickster",
                "Priest"
            ],
            "earlyLocationReacts": [
                {
                    "emote": "UTMarbleSeal",
                    "pointsGiven": 0,
                    "limit": 1,
                    "shortName": "Marble Seal",
                    "noConfirm": false,
                    "noLocation": false
                },
                {
                    "emote": "tomeOfTheMushroomTribesFungal",
                    "pointsGiven": 0,
                    "limit": 1,
                    "shortName": "Fungal Tome",
                    "noConfirm": false,
                    "noLocation": true
                },
                {
                    "emote": "daze",
                    "pointsGiven": 0,
                    "limit": 1,
                    "shortName": "Daze",
                    "noConfirm": false,
                    "noLocation": false
                },
                {
                    "emote": "Slow",
                    "pointsGiven": 0,
                    "limit": 2,
                    "shortName": "Slow",
                    "noConfirm": false,
                    "noLocation": false
                },
                {
                    "emote": "Collo",
                    "pointsGiven": 0,
                    "limit": 2,
                    "shortName": "Stun",
                    "noConfirm": false,
                    "noLocation": false
                },
                {
                    "emote": "Ogmur",
                    "pointsGiven": 1,
                    "limit": 1,
                    "shortName": "Armor Break",
                    "noConfirm": false,
                    "noLocation": false
                }
            ]
        },
        "nest": {
            "name": "Nest",
            "runType": "Nest",
            "runName": "Nest",
            "aliases": [],
            "enabled": true,
            "runLogName": "nestRuns",
            "keyEmote": "nestK",
            "headcountEmote": "nest",
            "headcountOnAfk": true,
            "thumbnail": "https://i.imgur.com/hUWc3IV.png",
            "color": "#ffd700",
            "twoPhase": true,
            "reacts": [
                "Curse",
                "Expose",
                "Warrior",
                "Paladin",
                "Knight",
                "Bard",
                "Trickster",
                "Priest"
            ],
            "keyCount": 3,
            "keyPopPoints": 5,
            "earlyLocationCost": 15,
            "vcCap" : 45,
            "pingRole": "nestReact",
            "isExalt": true,
            "earlyLocationReacts": [
                {
                    "emote": "UTMarbleSeal",
                    "pointsGiven": 0,
                    "limit": 1,
                    "shortName": "Marble Seal",
                    "noConfirm": false,
                    "noLocation": false
                },
                {
                    "emote": "Collo",
                    "pointsGiven": 0,
                    "limit": 2,
                    "shortName": "Stun",
                    "noConfirm": false,
                    "noLocation": true
                },
                {
                    "emote": "Slow",
                    "pointsGiven": 0,
                    "limit": 2,
                    "shortName": "Slow",
                    "noConfirm": false,
                    "noLocation": false
                },
                {
                    "emote": "Ogmur",
                    "pointsGiven": 1,
                    "limit": 1,
                    "shortName": "Armor Break",
                    "noConfirm": false,
                    "noLocation": false
                },
                {
                    "emote": "daze",
                    "pointsGiven": 0,
                    "limit": 1,
                    "shortName": "Daze",
                    "noConfirm": false,
                    "noLocation": false
                }
            ]
        },
        "Exaltednest": {
            "name": "Exalted Nest",
            "runType": "Exalted Nest",
            "runName": "Exalted Nest",
            "aliases": [
                "en",
                "enest",
                "exaltednest"
            ],
            "enabled": true,
            "runLogName": "nestRuns",
            "keyEmote": "nestK",
            "headcountEmote": "nest",
            "headcountOnAfk": true,
            "thumbnail": "https://i.imgur.com/hUWc3IV.png",
            "color": "#ffd700",
            "twoPhase": true,
            "keyCount": 3,
            "keyPopPoints": 5,
            "earlyLocationCost": 15,
            "vcCap": 45,
            "pingRole": "nestReact",
            "isExalt": true,
            "isExalted": true,
            "reacts": [
                "Knight",
                "Curse",
                "Expose",
                "Warrior",
                "Paladin",
                "Bard",
                "Trickster",
                "Priest"
            ],
            "earlyLocationReacts": [
                {
                    "emote": "UTMarbleSeal",
                    "pointsGiven": 0,
                    "limit": 1,
                    "shortName": "Marble Seal",
                    "noConfirm": false,
                    "noLocation": false
                },
                {
                    "emote": "Collo",
                    "pointsGiven": 0,
                    "limit": 2,
                    "shortName": "Stun",
                    "noConfirm": false,
                    "noLocation": true
                },
                {
                    "emote": "Slow",
                    "pointsGiven": 0,
                    "limit": 2,
                    "shortName": "Slow",
                    "noConfirm": false,
                    "noLocation": false
                },
                {
                    "emote": "Ogmur",
                    "pointsGiven": 1,
                    "limit": 1,
                    "shortName": "Armor Break",
                    "noConfirm": false,
                    "noLocation": false
                },
                {
                    "emote": "daze",
                    "pointsGiven": 0,
                    "limit": 1,
                    "shortName": "Daze",
                    "noConfirm": false,
                    "noLocation": false
                }
            ]
        },
        "fullskipnest": {
            "name": "Full-skip Nest",
            "runType": "Full-skip Nest",
            "runName": "Full-skip Nest",
            "aliases": [
                "fn",
                "fsnest"
            ],
            "enabled": true,
            "keyEmote": "nestK",
            "runLogName": "nestRuns",
            "headcountEmote": "nest",
            "headcountOnAfk": true,
            "thumbnail": "https://i.imgur.com/hUWc3IV.png",
            "color": "#ffd700",
            "expose": true,
            "twoPhase": true,
            "keyCount": 3,
            "keyPopPoints": 5,
            "earlyLocationCost": 15,
            "vcCap" : 45,
            "pingRole": "nestReact",
            "isExalt": true,
            "reacts": [
                "Knight",
                "Curse",
                "Expose",
                "Warrior",
                "Paladin",
                "Bard",
                "Trickster",
                "Priest"
            ],
            "earlyLocationReacts": [
                {
                    "emote": "UTMarbleSeal",
                    "pointsGiven": 0,
                    "limit": 1,
                    "shortName": "Marble Seal",
                    "noConfirm": false,
                    "noLocation": false
                },
                {
                    "emote": "Collo",
                    "pointsGiven": 0,
                    "limit": 2,
                    "shortName": "Stun",
                    "noConfirm": false,
                    "noLocation": true
                },
                {
                    "emote": "Slow",
                    "pointsGiven": 0,
                    "limit": 2,
                    "shortName": "Slow",
                    "noConfirm": false,
                    "noLocation": false
                },
                {
                    "emote": "Ogmur",
                    "pointsGiven": 1,
                    "limit": 1,
                    "shortName": "Armor Break",
                    "noConfirm": false,
                    "noLocation": false
                },
                {
                    "emote": "daze",
                    "pointsGiven": 0,
                    "limit": 1,
                    "shortName": "Daze",
                    "noConfirm": false,
                    "noLocation": false
                }
            ]
        },
        "Exaltedfullskipnest": {
            "name": "Exalted Full-skip Nest",
            "runType": "Exalted Full-skip Nest",
            "runName": "Exalted Full-skip Nest",
            "aliases": [
                "efn",
                "efsn",
                "efsnest"
            ],
            "enabled": true,
            "keyEmote": "nestK",
            "headcountEmote": "nest",
            "headcountOnAfk": true,
            "runLogName": "nestRuns",
            "thumbnail": "https://i.imgur.com/hUWc3IV.png",
            "color": "#ffd700",
            "reacts": [
                "Knight",
                "Curse",
                "Expose",
                "Warrior",
                "Paladin",
                "Bard",
                "Trickster",
                "Priest"
            ],
            "twoPhase": true,
            "keyCount": 3,
            "keyPopPoints": 5,
            "earlyLocationCost": 15,
            "vcCap": 45,
            "pingRole": "nestReact",
            "isExalt": true,
            "isExalted": true,
            "earlyLocationReacts": [
                {
                    "emote": "UTMarbleSeal",
                    "pointsGiven": 0,
                    "limit": 1,
                    "shortName": "Marble Seal",
                    "noConfirm": false,
                    "noLocation": false
                },
                {
                    "emote": "Collo",
                    "pointsGiven": 0,
                    "limit": 2,
                    "shortName": "Stun",
                    "noConfirm": false,
                    "noLocation": true
                },
                {
                    "emote": "Slow",
                    "pointsGiven": 0,
                    "limit": 2,
                    "shortName": "Slow",
                    "noConfirm": false,
                    "noLocation": false
                },
                {
                    "emote": "Ogmur",
                    "pointsGiven": 1,
                    "limit": 1,
                    "shortName": "Armor Break",
                    "noConfirm": false,
                    "noLocation": false
                },
                {
                    "emote": "daze",
                    "pointsGiven": 0,
                    "limit": 1,
                    "shortName": "Daze",
                    "noConfirm": false,
                    "noLocation": false
                }
            ]
        }
    }
}